{"count":1094,"next":"https://registry.hub.docker.com/v2/repositories/gitlab/gitlab-ce/tags?page=2","previous":null,"results":[{"creator":20229,"id":547475,"images":[{"architecture":"amd64","features":"","variant":null,"digest":"sha256:92e1ab7750d64f29178de26a0a857af9a9043d54ef27bf7e030c35f866d3e6ae","os":"linux","os_features":"","os_version":null,"size":1401311041,"status":"active","last_pulled":"2023-08-03T05:13:01.186344Z","last_pushed":"2023-08-01T17:12:46.968911Z"}],"last_updated":"2023-08-01T17:12:46.968911Z","last_updater":454693,"last_updater_username":"gitlabcibuild","name":"latest","repository":252439,"full_size":1401311041,"v2":true,"tag_status":"active","tag_last_pulled":"2023-08-03T05:13:01.186344Z","tag_last_pushed":"2023-08-01T17:12:46.968911Z","media_type":"application/vnd.docker.container.image.v1+json","content_type":"image","digest":"sha256:92e1ab7750d64f29178de26a0a857af9a9043d54ef27bf7e030c35f866d3e6ae"},{"creator":454693,"id":4253706,"images":[{"architecture":"amd64","features":"","variant":null,"digest":"sha256:6710b7dc0c5472fa906175076b7c5373650129d33334653b1786bffea4b18263","os":"linux","os_features":"","os_version":null,"size":1342581325,"status":"active","last_pulled":"2023-08-03T04:56:08.308876Z","last_pushed":"2023-08-03T02:32:31.951396Z"}],"last_updated":"2023-08-03T02:32:31.951396Z","last_updater":454693,"last_updater_username":"gitlabcibuild","name":"nightly","repository":252439,"full_size":1342581325,"v2":true,"tag_status":"active","tag_last_pulled":"2023-08-03T04:56:08.308876Z","tag_last_pushed":"2023-08-03T02:32:31.951396Z","media_type":"application/vnd.docker.container.image.v1+json","content_type":"image","digest":"sha256:6710b7dc0c5472fa906175076b7c5373650129d33334653b1786bffea4b18263"},{"creator":454693,"id":1400110,"images":[{"architecture":"amd64","features":"","variant":null,"digest":"sha256:92e1ab7750d64f29178de26a0a857af9a9043d54ef27bf7e030c35f866d3e6ae","os":"linux","os_features":"","os_version":null,"size":1401311041,"status":"active","last_pulled":"2023-08-03T05:13:01.186344Z","last_pushed":"2023-08-01T17:12:46.968911Z"}],"last_updated":"2023-08-01T17:12:43.354885Z","last_updater":454693,"last_updater_username":"gitlabcibuild","name":"rc","repository":252439,"full_size":1401311041,"v2":true,"tag_status":"active","tag_last_pulled":"2023-08-03T05:13:01.186344Z","tag_last_pushed":"2023-08-01T17:12:43.354885Z","media_type":"application/vnd.docker.container.image.v1+json","content_type":"image","digest":"sha256:92e1ab7750d64f29178de26a0a857af9a9043d54ef27bf7e030c35f866d3e6ae"},{"creator":454693,"id":485147608,"images":[{"architecture":"amd64","features":"","variant":null,"digest":"sha256:92e1ab7750d64f29178de26a0a857af9a9043d54ef27bf7e030c35f866d3e6ae","os":"linux","os_features":"","os_version":null,"size":1401311041,"status":"active","last_pulled":"2023-08-03T05:13:01.186344Z","last_pushed":"2023-08-01T17:12:46.968911Z"}],"last_updated":"2023-08-01T17:12:39.646052Z","last_updater":454693,"last_updater_username":"gitlabcibuild","name":"16.2.2-ce.0","repository":252439,"full_size":1401311041,"v2":true,"tag_status":"active","tag_last_pulled":"2023-08-03T05:13:01.186344Z","tag_last_pushed":"2023-08-01T17:12:39.646052Z","media_type":"application/vnd.docker.container.image.v1+json","content_type":"image","digest":"sha256:92e1ab7750d64f29178de26a0a857af9a9043d54ef27bf7e030c35f866d3e6ae"},{"creator":454693,"id":485079711,"images":[{"architecture":"amd64","features":"","variant":null,"digest":"sha256:1623604126e143f112c515d56f2bac434498040aee5dcc4b132d484afac95f93","os":"linux","os_features":"","os_version":null,"size":1392156729,"status":"active","last_pulled":"2023-08-03T04:47:14.534433Z","last_pushed":"2023-08-01T15:33:57.597519Z"}],"last_updated":"2023-08-01T15:33:57.720057Z","last_updater":454693,"last_updater_username":"gitlabcibuild","name":"16.0.8-ce.0","repository":252439,"full_size":1392156729,"v2":true,"tag_status":"active","tag_last_pulled":"2023-08-03T04:47:14.534433Z","tag_last_pushed":"2023-08-01T15:33:57.720057Z","media_type":"application/vnd.docker.container.image.v1+json","content_type":"image","digest":"sha256:1623604126e143f112c515d56f2bac434498040aee5dcc4b132d484afac95f93"},{"creator":454693,"id":485064266,"images":[{"architecture":"amd64","features":"","variant":null,"digest":"sha256:623628b6f6601b6a9372f23aec7c412da9be942bc6d5193cdc4df8d2bed9d2aa","os":"linux","os_features":"","os_version":null,"size":1380254435,"status":"active","last_pulled":"2023-08-03T05:00:32.745032Z","last_pushed":"2023-08-01T15:13:00.500539Z"}],"last_updated":"2023-08-01T15:13:00.609092Z","last_updater":454693,"last_updater_username":"gitlabcibuild","name":"16.1.3-ce.0","repository":252439,"full_size":1380254435,"v2":true,"tag_status":"active","tag_last_pulled":"2023-08-03T05:00:32.745032Z","tag_last_pushed":"2023-08-01T15:13:00.609092Z","media_type":"application/vnd.docker.container.image.v1+json","content_type":"image","digest":"sha256:623628b6f6601b6a9372f23aec7c412da9be942bc6d5193cdc4df8d2bed9d2aa"},{"creator":454693,"id":482642365,"images":[{"architecture":"amd64","features":"","variant":null,"digest":"sha256:798b18325a90851922c916fcded34d1ba7decf810a311765b43e43f452bf564c","os":"linux","os_features":"","os_version":null,"size":1379029536,"status":"active","last_pulled":"2023-08-03T05:04:50.822648Z","last_pushed":"2023-07-27T21:04:58.020275Z"}],"last_updated":"2023-07-27T21:04:58.133663Z","last_updater":454693,"last_updater_username":"gitlabcibuild","name":"15.11.13-ce.0","repository":252439,"full_size":1379029536,"v2":true,"tag_status":"active","tag_last_pulled":"2023-08-03T05:04:50.822648Z","tag_last_pushed":"2023-07-27T21:04:58.133663Z","media_type":"application/vnd.docker.container.image.v1+json","content_type":"image","digest":"sha256:798b18325a90851922c916fcded34d1ba7decf810a311765b43e43f452bf564c"},{"creator":454693,"id":480932644,"images":[{"architecture":"amd64","features":"","variant":null,"digest":"sha256:bb54c14b0afbf478752aa60b23735d3bcf7defbf4da2da7666ccf6db4136993c","os":"linux","os_features":"","os_version":null,"size":1400049282,"status":"active","last_pulled":"2023-08-03T05:11:12.601465Z","last_pushed":"2023-07-25T11:18:03.755867Z"}],"last_updated":"2023-07-25T11:17:56.859197Z","last_updater":454693,"last_updater_username":"gitlabcibuild","name":"16.2.1-ce.0","repository":252439,"full_size":1400049282,"v2":true,"tag_status":"active","tag_last_pulled":"2023-08-03T05:11:12.601465Z","tag_last_pushed":"2023-07-25T11:17:56.859197Z","media_type":"application/vnd.docker.container.image.v1+json","content_type":"image","digest":"sha256:bb54c14b0afbf478752aa60b23735d3bcf7defbf4da2da7666ccf6db4136993c"},{"creator":454693,"id":479620456,"images":[{"architecture":"amd64","features":"","variant":null,"digest":"sha256:c62e5acff77f8930790b68752391100ad6b9e468564b2014ac4a58394db2a67c","os":"linux","os_features":"","os_version":null,"size":1400040674,"status":"active","last_pulled":"2023-08-03T04:59:13.233872Z","last_pushed":"2023-07-22T13:19:32.66914Z"}],"last_updated":"2023-07-22T13:19:26.588011Z","last_updater":454693,"last_updater_username":"gitlabcibuild","name":"16.2.0-ce.0","repository":252439,"full_size":1400040674,"v2":true,"tag_status":"active","tag_last_pulled":"2023-08-03T04:59:13.233872Z","tag_last_pushed":"2023-07-22T13:19:26.588011Z","media_type":"application/vnd.docker.container.image.v1+json","content_type":"image","digest":"sha256:c62e5acff77f8930790b68752391100ad6b9e468564b2014ac4a58394db2a67c"},{"creator":454693,"id":476471102,"images":[{"architecture":"amd64","features":"","variant":null,"digest":"sha256:95f1353ab1fa93f756333d404a9bf5770a5aaeb8613badf1286823030bce66de","os":"linux","os_features":"","os_version":null,"size":1379011960,"status":"active","last_pulled":"2023-08-03T04:41:39.222696Z","last_pushed":"2023-07-17T11:26:36.441312Z"}],"last_updated":"2023-07-17T11:26:36.533798Z","last_updater":454693,"last_updater_username":"gitlabcibuild","name":"15.11.12-ce.0","repository":252439,"full_size":1379011960,"v2":true,"tag_status":"active","tag_last_pulled":"2023-08-03T04:41:39.222696Z","tag_last_pushed":"2023-07-17T11:26:36.533798Z","media_type":"application/vnd.docker.container.image.v1+json","content_type":"image","digest":"sha256:95f1353ab1fa93f756333d404a9bf5770a5aaeb8613badf1286823030bce66de"}]}
