{"count":1119,"next":"https://registry.hub.docker.com/v2/repositories/gitlab/gitlab-ee/tags?page=2\u0026page_size=10","previous":null,"results":[{"creator":454693,"id":1015100,"images":[{"architecture":"amd64","features":"","variant":null,"digest":"sha256:46a503c045361b61fd64eff56ebc4045d16d0adf8dbca0f6417c2311e85a788f","os":"linux","os_features":"","os_version":null,"size":1482588993,"status":"active","last_pulled":"2023-12-19T04:59:31.789598Z","last_pushed":"2023-12-13T16:56:52.876965Z"}],"last_updated":"2023-12-13T16:56:52.876965Z","last_updater":454693,"last_updater_username":"gitlabcibuild","name":"latest","repository":335675,"full_size":1482588993,"v2":true,"tag_status":"active","tag_last_pulled":"2023-12-19T04:59:31.789598Z","tag_last_pushed":"2023-12-13T16:56:52.876965Z","media_type":"application/vnd.docker.container.image.v1+json","content_type":"image","digest":"sha256:46a503c045361b61fd64eff56ebc4045d16d0adf8dbca0f6417c2311e85a788f"},{"creator":454693,"id":4580535,"images":[{"architecture":"amd64","features":"","variant":null,"digest":"sha256:c3df71d48596d2dee8f870d7ec292489a1433f901b0e4f72a8c378a655f2135c","os":"linux","os_features":"","os_version":null,"size":1487950605,"status":"active","last_pulled":"2023-12-19T04:56:21.424738Z","last_pushed":"2023-12-19T02:27:19.416836Z"}],"last_updated":"2023-12-19T02:27:19.416836Z","last_updater":454693,"last_updater_username":"gitlabcibuild","name":"nightly","repository":335675,"full_size":1487950605,"v2":true,"tag_status":"active","tag_last_pulled":"2023-12-19T04:56:21.424738Z","tag_last_pushed":"2023-12-19T02:27:19.416836Z","media_type":"application/vnd.docker.container.image.v1+json","content_type":"image","digest":"sha256:c3df71d48596d2dee8f870d7ec292489a1433f901b0e4f72a8c378a655f2135c"},{"creator":454693,"id":567565516,"images":[{"architecture":"amd64","features":"","variant":null,"digest":"sha256:b9d9f1250e2f9fb6885572bac7cd7acb21f096a5e7427b18b9ceda13e8962519","os":"linux","os_features":"","os_version":null,"size":1467815760,"status":"active","last_pulled":"2023-12-19T05:01:42.168884Z","last_pushed":"2023-12-13T17:01:13.854453Z"}],"last_updated":"2023-12-13T17:01:13.962248Z","last_updater":454693,"last_updater_username":"gitlabcibuild","name":"16.4.4-ee.0","repository":335675,"full_size":1467815760,"v2":true,"tag_status":"active","tag_last_pulled":"2023-12-19T05:01:42.168884Z","tag_last_pushed":"2023-12-13T17:01:13.962248Z","media_type":"application/vnd.docker.container.image.v1+json","content_type":"image","digest":"sha256:b9d9f1250e2f9fb6885572bac7cd7acb21f096a5e7427b18b9ceda13e8962519"},{"creator":454693,"id":567565159,"images":[{"architecture":"amd64","features":"","variant":null,"digest":"sha256:906ac0c3d11a952296845ebdb1bbdb5e4aef879150baa5be6a4a94afc4204d28","os":"linux","os_features":"","os_version":null,"size":1475460585,"status":"active","last_pulled":"2023-12-19T05:08:15.651658Z","last_pushed":"2023-12-13T17:00:46.361139Z"}],"last_updated":"2023-12-13T17:00:46.444718Z","last_updater":454693,"last_updater_username":"gitlabcibuild","name":"16.5.4-ee.0","repository":335675,"full_size":1475460585,"v2":true,"tag_status":"active","tag_last_pulled":"2023-12-19T05:08:15.651658Z","tag_last_pushed":"2023-12-13T17:00:46.444718Z","media_type":"application/vnd.docker.container.image.v1+json","content_type":"image","digest":"sha256:906ac0c3d11a952296845ebdb1bbdb5e4aef879150baa5be6a4a94afc4204d28"},{"creator":454693,"id":1400151,"images":[{"architecture":"amd64","features":"","variant":null,"digest":"sha256:46a503c045361b61fd64eff56ebc4045d16d0adf8dbca0f6417c2311e85a788f","os":"linux","os_features":"","os_version":null,"size":1482588993,"status":"active","last_pulled":"2023-12-19T04:59:31.789598Z","last_pushed":"2023-12-13T16:56:52.876965Z"}],"last_updated":"2023-12-13T16:56:48.972585Z","last_updater":454693,"last_updater_username":"gitlabcibuild","name":"rc","repository":335675,"full_size":1482588993,"v2":true,"tag_status":"active","tag_last_pulled":"2023-12-19T04:59:31.789598Z","tag_last_pushed":"2023-12-13T16:56:48.972585Z","media_type":"application/vnd.docker.container.image.v1+json","content_type":"image","digest":"sha256:46a503c045361b61fd64eff56ebc4045d16d0adf8dbca0f6417c2311e85a788f"},{"creator":454693,"id":567562839,"images":[{"architecture":"amd64","features":"","variant":null,"digest":"sha256:46a503c045361b61fd64eff56ebc4045d16d0adf8dbca0f6417c2311e85a788f","os":"linux","os_features":"","os_version":null,"size":1482588993,"status":"active","last_pulled":"2023-12-19T04:59:31.789598Z","last_pushed":"2023-12-13T16:56:52.876965Z"}],"last_updated":"2023-12-13T16:56:46.230926Z","last_updater":454693,"last_updater_username":"gitlabcibuild","name":"16.6.2-ee.0","repository":335675,"full_size":1482588993,"v2":true,"tag_status":"active","tag_last_pulled":"2023-12-19T04:59:31.789598Z","tag_last_pushed":"2023-12-13T16:56:46.230926Z","media_type":"application/vnd.docker.container.image.v1+json","content_type":"image","digest":"sha256:46a503c045361b61fd64eff56ebc4045d16d0adf8dbca0f6417c2311e85a788f"},{"creator":454693,"id":558240832,"images":[{"architecture":"amd64","features":"","variant":null,"digest":"sha256:b8c20e7868637796c3e8cd7602d0d28c9b8c212df7ce944f684b3968486eae32","os":"linux","os_features":"","os_version":null,"size":1469982071,"status":"active","last_pulled":"2023-12-19T05:01:40.244452Z","last_pushed":"2023-11-30T18:46:30.911868Z"}],"last_updated":"2023-11-30T18:46:31.011456Z","last_updater":454693,"last_updater_username":"gitlabcibuild","name":"16.4.3-ee.0","repository":335675,"full_size":1469982071,"v2":true,"tag_status":"active","tag_last_pulled":"2023-12-19T05:01:40.244452Z","tag_last_pushed":"2023-11-30T18:46:31.011456Z","media_type":"application/vnd.docker.container.image.v1+json","content_type":"image","digest":"sha256:b8c20e7868637796c3e8cd7602d0d28c9b8c212df7ce944f684b3968486eae32"},{"creator":454693,"id":558230146,"images":[{"architecture":"amd64","features":"","variant":null,"digest":"sha256:ec57c971b9480d25bc4f3b4e90dd0e5b71c93077eb73b78a131a45d21852b823","os":"linux","os_features":"","os_version":null,"size":1477818578,"status":"active","last_pulled":"2023-12-19T05:10:09.632607Z","last_pushed":"2023-11-30T18:24:54.386843Z"}],"last_updated":"2023-11-30T18:24:54.474942Z","last_updater":454693,"last_updater_username":"gitlabcibuild","name":"16.5.3-ee.0","repository":335675,"full_size":1477818578,"v2":true,"tag_status":"active","tag_last_pulled":"2023-12-19T05:10:09.632607Z","tag_last_pushed":"2023-11-30T18:24:54.474942Z","media_type":"application/vnd.docker.container.image.v1+json","content_type":"image","digest":"sha256:ec57c971b9480d25bc4f3b4e90dd0e5b71c93077eb73b78a131a45d21852b823"},{"creator":454693,"id":558220521,"images":[{"architecture":"amd64","features":"","variant":null,"digest":"sha256:9443734260b96694058afe05eba1b2c24da185ba419dbf8c417efbbf32ea7fbe","os":"linux","os_features":"","os_version":null,"size":1484830776,"status":"active","last_pulled":"2023-12-19T05:02:04.098209Z","last_pushed":"2023-11-30T18:03:06.184175Z"}],"last_updated":"2023-11-30T18:03:00.105684Z","last_updater":454693,"last_updater_username":"gitlabcibuild","name":"16.6.1-ee.0","repository":335675,"full_size":1484830776,"v2":true,"tag_status":"active","tag_last_pulled":"2023-12-19T05:02:04.098209Z","tag_last_pushed":"2023-11-30T18:03:00.105684Z","media_type":"application/vnd.docker.container.image.v1+json","content_type":"image","digest":"sha256:9443734260b96694058afe05eba1b2c24da185ba419dbf8c417efbbf32ea7fbe"},{"creator":454693,"id":550153367,"images":[{"architecture":"amd64","features":"","variant":null,"digest":"sha256:1e63c5021e89437f42b6d07807609786fa6e9c1c9006ea07f3c172d035dd7064","os":"linux","os_features":"","os_version":null,"size":1481622314,"status":"active","last_pulled":"2023-12-19T04:39:30.190861Z","last_pushed":"2023-11-16T13:23:41.134219Z"}],"last_updated":"2023-11-16T13:23:36.188269Z","last_updater":454693,"last_updater_username":"gitlabcibuild","name":"16.6.0-ee.0","repository":335675,"full_size":1481622314,"v2":true,"tag_status":"active","tag_last_pulled":"2023-12-19T04:39:30.190861Z","tag_last_pushed":"2023-11-16T13:23:36.188269Z","media_type":"application/vnd.docker.container.image.v1+json","content_type":"image","digest":"sha256:1e63c5021e89437f42b6d07807609786fa6e9c1c9006ea07f3c172d035dd7064"}]}
